avmesos/__init__.py
avmesos/exceptions.py
avmesos/http.py
avmesos/recordio.py
avmesos/cli/__init__.py
avmesos/cli/config.py
avmesos/cli/constants.py
avmesos/cli/docopt.py
avmesos/cli/exceptions.py
avmesos/cli/http.py
avmesos/cli/mesos-cli.py
avmesos/cli/mesos.py
avmesos/cli/settings.py
avmesos/cli/util.py
avmesos/cli/plugins/__init__.py
avmesos/cli/plugins/base.py
avmesos/cli/plugins/agent/__init__.py
avmesos/cli/plugins/agent/main.py
avmesos/cli/plugins/config/__init__.py
avmesos/cli/plugins/config/main.py
avmesos/cli/plugins/framework/__init__.py
avmesos/cli/plugins/framework/main.py
avmesos/cli/plugins/task/__init__.py
avmesos/cli/plugins/task/main.py
avmesos_cli-1.0.0.data/scripts/mesos-cli
avmesos_cli-1.0.0.dist-info/METADATA
avmesos_cli-1.0.0.dist-info/WHEEL
avmesos_cli-1.0.0.dist-info/top_level.txt
avmesos_cli-1.0.0.dist-info/RECORD
