Metadata-Version: 2.1
Name: avmesos-cli
Version: 1.0.0
Summary: Apache Mesos CLI
Home-page: https://www.aventer.biz/
Author: AVENTER UG (haftungsbeschraenkt)
Author-email: support@aventer.biz
License: Apache License 2.0
Requires-Python: >=3.6
Requires-Dist: backports.functools-lru-cache (>=1.2.1)
Requires-Dist: configparser (>=3.5.0)
Requires-Dist: docopt (>=0.6.2)
Requires-Dist: isort (>=4.2.5)
Requires-Dist: kazoo (>=2.5.0)
Requires-Dist: lazy-object-proxy (>=1.2.2)
Requires-Dist: parse (>=1.8.0)
Requires-Dist: Pygments (>=2.7.4)
Requires-Dist: PyInstaller (>=3.6)
Requires-Dist: six (>=1.10.0)
Requires-Dist: tenacity (>=4.12.0)
Requires-Dist: toml (>=0.9.2)
Requires-Dist: wrapt (>=1.10.8)
Requires-Dist: tox (>=3.2.1)
Requires-Dist: ujson (>=5.8.0)
